fortran_module_usage/__init__.py
fortran_module_usage/check_fortran_module_usage.py
pyfortran-0.1.2.dist-info/licenses/LICENSE
pyfortran-0.1.2.dist-info/METADATA
pyfortran-0.1.2.dist-info/WHEEL
pyfortran-0.1.2.dist-info/entry_points.txt
pyfortran-0.1.2.dist-info/top_level.txt
pyfortran-0.1.2.dist-info/RECORD
