Metadata-Version: 2.4
Name: pyfortran
Version: 0.1.2
Summary: Python package for Fortran-based utilities, including a program to determine subroutine usage in a Fortran module.
Author-email: DART <dart@ucar.edu>
License: Apache-2.0
Project-URL: Homepage, https://github.com/NCAR/DART
Project-URL: Repository, https://github.com/NCAR/DART
Classifier: Programming Language :: Python :: 3
Classifier: License :: OSI Approved :: Apache Software License
Classifier: Operating System :: OS Independent
Requires-Python: >=3.8
License-File: LICENSE
Dynamic: license-file
